leist_converter/__init__.py
leist_converter/convert.py
leist_converter/resources/word_mappings.json
leist_converter-0.1.3.dist-info/LICENSE
leist_converter-0.1.3.dist-info/METADATA
leist_converter-0.1.3.dist-info/WHEEL
leist_converter-0.1.3.dist-info/top_level.txt
leist_converter-0.1.3.dist-info/RECORD
