Metadata-Version: 2.2
Name: leist_converter
Version: 0.1.3
Summary: Eine Python-Bibliothek zur Umwandlung von Texten in altdeutsche Schreibweise, inklusive französischer Lehnwörter.
Author: Jonah Wendel
License: MIT License
Project-URL: Homepage, https://github.com/w-jonah/leist_converter.git
Project-URL: Repository, https://github.com/w-jonah/leist_converter.git
Requires-Python: >=3.8
License-File: LICENSE
